{
  "msg":"true",
  "items":{
    "datasets":[
      {
        "id":35,
        "explains":"数据备份失败！！！",
        "backuptime":"Aug 11, 2017 12:00:00 AM"
      },
      {
        "id":35,
        "explains":"数据备份失败！！！",
        "backuptime":"Aug 11, 2017 12:00:00 AM"
      },
      {
        "id":35,
        "explains":"数据备份失败！！！",
        "backuptime":"Aug 11, 2017 12:00:00 AM"
      },
      {
        "id":35,
        "explains":"数据备份失败！！！",
        "backuptime":"Aug 11, 2017 12:00:00 AM"
      },
      {
        "id":35,
        "explains":"数据备份失败！！！",
        "backuptime":"Aug 11, 2017 12:00:00 AM"
      },
      {
        "id":35,
        "explains":"数据备份失败！！！",
        "backuptime":"Aug 11, 2017 12:00:00 AM"
      }
    ],
    "Statistics":{
      "total_pages":3,
      "total_data":26
    }
  }
}